uplan/__init__.py
uplan/init.py
uplan/main.py
uplan/process.py
uplan/question.py
uplan/models/__init__.py
uplan/models/todo.py
uplan/templates/__init__.py
uplan/templates/dev/plan.toml
uplan/templates/dev/todo.toml
uplan/templates/dev_kr/plan.toml
uplan/templates/dev_kr/todo.toml
uplan/utils/__init__.py
uplan/utils/data.py
uplan/utils/display.py
uplan/utils/file.py
uplan/utils/provider.py
uplan/utils/text.py
uplan-1.0.2.dist-info/METADATA
uplan-1.0.2.dist-info/WHEEL
uplan-1.0.2.dist-info/entry_points.txt
uplan-1.0.2.dist-info/top_level.txt
uplan-1.0.2.dist-info/RECORD
