Metadata-Version: 2.2
Name: uplan
Version: 1.0.2
Summary: 📋uPlan - AI-powered development planning automation tool that generates structured project documents and to-do lists. Streamlines your planning workflow with template-based questions, efficient AI usage, and TOML-formatted outputs. Supports multiple AI models and offers customizable templates for development planning.
Author-email: EasyDev <easydevv@gmail.com>
Project-URL: source, https://github.com/easydevv/uplan
Classifier: Programming Language :: Python :: 3.12
Classifier: License :: OSI Approved :: MIT License
Classifier: Operating System :: OS Independent
Requires-Python: >=3.12
Requires-Dist: litellm>=1.63.6
Requires-Dist: rich>=13.9.4
Requires-Dist: tomli-w>=1.2.0
